fabric_maverick-0.1.1.dev2.dist-info/licenses/AUTHORS.md
fabric_maverick-0.1.1.dev2.dist-info/licenses/LICENSE
knnpy/__init__.py
knnpy/base.py
knnpy/comparers.py
knnpy/config.py
knnpy/report.py
knnpy/token_provider.py
knnpy/utils.py
knnpy/validators.py
fabric_maverick-0.1.1.dev2.dist-info/METADATA
fabric_maverick-0.1.1.dev2.dist-info/WHEEL
fabric_maverick-0.1.1.dev2.dist-info/top_level.txt
fabric_maverick-0.1.1.dev2.dist-info/RECORD
