Metadata-Version: 2.4
Name: fabric_maverick
Version: 0.1.1.dev2
Summary: A Fabric Package for Semantic/Dataset validation
Author: MAQ Software
Author-email: Nisarg Patel <nisargp@maqsoftware.com>
Maintainer-email: Nisarg Patel <nisargp@maqsoftware.com>, Kunal Sarda <kunals@maqsoftware.com>, Milankumar Nakum <nakumm@maqsoftware.com>
License: MIT License
Keywords: Fabric,Microsoft Fabric,Sempy,Semantic Model,Report,Report Compare
Classifier: Development Status :: 3 - Alpha
Classifier: Intended Audience :: Developers
Classifier: Intended Audience :: Education
Classifier: Intended Audience :: Science/Research
Classifier: Programming Language :: Python :: 3.10
Classifier: Programming Language :: Python :: 3 :: Only
Classifier: Framework :: Jupyter
Requires-Python: >=3.10,<3.12
License-File: LICENSE
License-File: AUTHORS.md
Requires-Dist: thefuzz
Requires-Dist: semantic-link-sempy>=0.11.0
Provides-Extra: test
Requires-Dist: pytest>=8.2.1; extra == "test"
Dynamic: license-file
Dynamic: requires-python
